shopen/__init__.py
shopen/_version.py
shopen/open.py
shopen/py.typed
shopen-0.2.2.dist-info/METADATA
shopen-0.2.2.dist-info/WHEEL
shopen-0.2.2.dist-info/licenses/LICENSE.txt
shopen-0.2.2.dist-info/RECORD
