Metadata-Version: 2.3
Name: shopen
Version: 0.2.2
Summary: Proper implementation of os.startfile to launch a target file/URL
Project-URL: Documentation, https://github.com/dbarnett/py-shopen#readme
Project-URL: Issues, https://github.com/dbarnett/py-shopen/issues
Project-URL: Source, https://github.com/dbarnett/py-shopen
Author-email: David Barnett <david@mumind.me>
License-Expression: MIT
License-File: LICENSE.txt
Keywords: os
Classifier: Development Status :: 4 - Beta
Classifier: Programming Language :: Python
Classifier: Programming Language :: Python :: 3.8
Classifier: Programming Language :: Python :: 3.9
Classifier: Programming Language :: Python :: 3.10
Classifier: Programming Language :: Python :: 3.11
Classifier: Programming Language :: Python :: 3.12
Classifier: Programming Language :: Python :: Implementation :: CPython
Classifier: Programming Language :: Python :: Implementation :: PyPy
Requires-Python: >=3.8
Provides-Extra: dev
Requires-Dist: pytest; extra == 'dev'
Requires-Dist: pytest-mock; extra == 'dev'
Requires-Dist: pytest-subprocess; extra == 'dev'
